[
    {
        "name" : "Falcon 1",
        "rocketFamily" : "Falcon",
        "providerName" : "SpaceX",
        "numberOfVariants" : 1,
        "orbitClass" : "Orbital",
        "reusable" : "Expended",
        "status" : "Retired",
    },
    {
        "name" : "Falcon 9",
        "rocketFamily" : "Falcon",
        "providerName" : "SpaceX",
        "numberOfVariants" : 7,
        "orbitClass" : "Orbital",
        "reusable" : "Partially",
        "status" : "Operational",
    },
    {
        "name" : "Falcon Heavy",
        "rocketFamily" : "Falcon",
        "providerName" : "SpaceX",
        "numberOfVariants" : 1,
        "orbitClass" : "Suborbital",
        "reusable" : "Partially",
        "status" : "Grounded",
    },
    {
        "name" : "Starship",
        "rocketFamily" : "Starship",
        "providerName" : "SpaceX",
        "numberOfVariants" : 6,
        "orbitClass" : "Suborbital",
        "reusable" : "Fully",
        "status" : "Development",
    },
    {
        "name" : "Atlas V",
        "rocketFamily" : "Atlas",
        "providerName" : "ULA",
        "numberOfVariants" : 12,
        "orbitClass" : "Orbital",
        "reusable" : "Expended",
        "status" : "Testing",
    },
]
